{
  "university": "University of Houston",
  "major": "B.S. in Exercise Science (Health Professions Option)",
  "total_credit_hours": 120,
  "graduation_rules": [
    "Minimum 2.00 GPA in cumulative, major and minor work to graduate",
    "C\u2212 rule: maximum of 6 hours of grades below C\u2212 allowed in major courses",
    "Pre\u2011requisite rule: must earn C\u2212 or better in all prerequisite courses in order to take subsequent courses",
    "See residency rule in UH catalog",
    "Maximum of 6 withdrawals (W\u2019s) allowed during entire undergraduate career",
    "Minimum of 36 advanced (3000\u2011 or 4000\u2011level) hours and 120 total hours required to graduate",
    "Maximum of 66 lower\u2011level transfer hours may be applied toward the UH degree"
  ],
  "requirements_categories": [
    "Core",
    "Major Prerequisites",
    "Major Core",
    "Major Electives"
  ],
  "courses": [
    {
      "id": "ENGL 1301",
      "name": "First Year Writing I",
      "credits": 3,
      "prerequisites": [],
      "requirement_type": "Core",
      "level": 1000
    },
    {
      "id": "ENGL 1302",
      "name": "First Year Writing II",
      "credits": 3,
      "prerequisites": [
        "ENGL 1301"
      ],
      "requirement_type": "Core",
      "level": 1000
    },
    {
      "id": "HIST 1301",
      "name": "U.S. History to 1877",
      "credits": 3,
      "prerequisites": [],
      "requirement_type": "Core",
      "level": 1000
    },
    {
      "id": "HIST 1302",
      "name": "U.S. History since 1877",
      "credits": 3,
      "prerequisites": [],
      "requirement_type": "Core",
      "level": 1000
    },
    {
      "id": "GOVT 2305",
      "name": "U.S. Government: Congress, President, and Court",
      "credits": 3,
      "prerequisites": [],
      "requirement_type": "Core",
      "level": 2000
    },
    {
      "id": "GOVT 2306",
      "name": "U.S. and Texas Constitutions and Politics",
      "credits": 3,
      "prerequisites": [],
      "requirement_type": "Core",
      "level": 2000
    },
    {
      "id": "KIN 1302",
      "name": "Foundations of Kinesiology",
      "credits": 3,
      "prerequisites": [],
      "requirement_type": "Major Prerequisites",
      "level": 1000
    },
    {
      "id": "KIN 1352",
      "name": "Foundations of Fitness and Sport",
      "credits": 3,
      "prerequisites": [],
      "requirement_type": "Major Prerequisites",
      "level": 1000
    },
    {
      "id": "BIOL 1355",
      "name": "Human Anatomy and Physiology I",
      "credits": 3,
      "prerequisites": [],
      "requirement_type": "Major Prerequisites",
      "level": 1000
    },
    {
      "id": "BIOL 1155",
      "name": "Human Anatomy and Physiology I Lab",
      "credits": 1,
      "prerequisites": [
        "BIOL 1355"
      ],
      "requirement_type": "Major Prerequisites",
      "level": 1000
    },
    {
      "id": "CHEM 1301",
      "name": "Introductory Chemistry",
      "credits": 3,
      "prerequisites": [],
      "requirement_type": "Major Prerequisites",
      "level": 1000
    },
    {
      "id": "CHEM 1101",
      "name": "Introductory Chemistry Lab",
      "credits": 1,
      "prerequisites": [
        "CHEM 1301"
      ],
      "requirement_type": "Major Prerequisites",
      "level": 1000
    },
    {
      "id": "PHYS 1301",
      "name": "College Physics I",
      "credits": 3,
      "prerequisites": [],
      "requirement_type": "Major Prerequisites",
      "level": 1000
    },
    {
      "id": "PHYS 1101",
      "name": "College Physics I Lab",
      "credits": 1,
      "prerequisites": [
        "PHYS 1301"
      ],
      "requirement_type": "Major Prerequisites",
      "level": 1000
    },
    {
      "id": "MATH 2413",
      "name": "Calculus I",
      "credits": 4,
      "prerequisites": [],
      "requirement_type": "Major Prerequisites",
      "level": 2000
    },
    {
      "id": "KIN 3306",
      "name": "Biomechanics",
      "credits": 3,
      "prerequisites": [
        "KIN 1302"
      ],
      "requirement_type": "Major Core",
      "level": 3000
    },
    {
      "id": "KIN 3307",
      "name": "Motor Control and Learning",
      "credits": 3,
      "prerequisites": [
        "KIN 1302"
      ],
      "requirement_type": "Major Core",
      "level": 3000
    },
    {
      "id": "KIN 4303",
      "name": "Exercise Testing and Prescription",
      "credits": 3,
      "prerequisites": [
        "KIN 3306"
      ],
      "requirement_type": "Major Core",
      "level": 4000
    },
    {
      "id": "KIN 4335",
      "name": "Exercise Physiology",
      "credits": 3,
      "prerequisites": [
        "BIOL 1355"
      ],
      "requirement_type": "Major Core",
      "level": 4000
    },
    {
      "id": "KIN 4365",
      "name": "Strength and Conditioning",
      "credits": 3,
      "prerequisites": [
        "KIN 3306"
      ],
      "requirement_type": "Major Core",
      "level": 4000
    },
    {
      "id": "KIN 4311",
      "name": "Clinical Exercise Physiology",
      "credits": 3,
      "prerequisites": [
        "KIN 4303"
      ],
      "requirement_type": "Major Electives",
      "level": 4000
    },
    {
      "id": "KIN 4375",
      "name": "Pathophysiology for Exercise Science",
      "credits": 3,
      "prerequisites": [
        "BIOL 1355"
      ],
      "requirement_type": "Major Electives",
      "level": 4000
    }
  ]
}